{"about.md":"BLFi4ax0","bookmarks.md":"D2SPPV_O","contact.md":"DTO6o45L","en_about.md":"B257KGYl","en_contact.md":"DnjWpFnq","en_index.md":"C565dtSg","en_memo_index.md":"WWMqiITx","index.md":"CJTUvUlH","memo_apple_homebrew.md":"BrgDDaxY","memo_apple_macos.md":"D3XXblNl","memo_git_common.md":"Dxe6078Z","memo_git_config.md":"DacY2ELM","memo_git_project.md":"CZhFYSU4","memo_git_upload-executable-permission.md":"CH1BrTcw","memo_index.md":"26W2HXD0","memo_microsoft_developer-register.md":"DYOrM9ls","memo_microsoft_gamingoverlay.md":"B_4gRByV","memo_microsoft_hyperv-damage.md":"CLPfziog","memo_microsoft_oobe.md":"vXZYzhBJ","memo_microsoft_remote-signed.md":"DCNEALi_","memo_microsoft_time-sync.md":"DqD5dUgr","memo_microsoft_virtual-display.md":"dq47qUH2","memo_microsoft_wsreset.md":"DTfHwcSk","memo_node_execution-path-space.md":"mFT-r4pN","memo_node_registry.md":"B-OHz21N","memo_via_parsec.md":"3JxkUhqG","memo_web_applet-https.md":"DCEKvmJT","memo_web_await-catch.md":"DFMuQmjn","memo_web_nginx.md":"Bu7te0JE","memo_web_node-registry.md":"Cey0SZs6","memo_web_num2arr.md":"DgulVhTh","memo_web_pnpm.md":"DdnUlAnc","memo_web_vmodel-loop-error.md":"n1Fb9f5z","memo_web_vue-call-parent-method.md":"DC263Uvj","memo_web_yarn-private-error.md":"CNSFngif"}
