{"about.md":"93b1d35d","bookmarks.md":"75cb7c26","contact.md":"cd47bcae","en_index.md":"6838d5c2","en_memo_index.md":"0b50965e","index.md":"d5ce8b4f","en_contact.md":"f736b813","en_about.md":"bc0fc57e","memo_index.md":"8fd39549","memo_microsoft_hyperv-damage.md":"9fd5626b","memo_microsoft_remote-signed.md":"95d3259c","memo_microsoft_virtual-display.md":"9faca163","memo_node_registry.md":"0c3192dd","memo_via_parsec.md":"90ce4bc1","memo_web_await-catch.md":"a220160d","memo_web_node-registry.md":"c7ce48fd","memo_web_num2arr.md":"0ae2d3d3","memo_web_pnpm.md":"5e430e14","memo_web_vmodel-loop-error.md":"cdcd01e3","memo_web_vue-call-parent-method.md":"9adc32e9","memo_web_yarn-private-error.md":"af30489d","memo_web_applet-https.md":"e0ac687a","memo_git_project.md":"151a9ba8","memo_apple_homebrew.md":"c8c84a6f","memo_git_common.md":"6f387789","memo_git_config.md":"c7e7933e","memo_web_nginx.md":"513f1c34","memo_apple_macos.md":"1e1958fe"}
