{"memo_web_applet-https.md":"9b3df1e9","memo_web_await-catch.md":"3a394c7c","memo_web_nginx.md":"2f6b7b65","memo_web_node-registry.md":"dbd78829","memo_web_num2arr.md":"fe293034","memo_web_yarn-private-error.md":"6533aba2","memo_index.md":"044584e6","memo_web_vue-call-parent-method.md":"263d7ace","memo_web_pnpm.md":"4649ca6f","memo_node_registry.md":"1018daa8","memo_microsoft_virtual-display.md":"2b2e698c","contact.md":"027ceb8b","en_about.md":"48930b2f","memo_microsoft_hyperv-damage.md":"9f9e099d","en_index.md":"bf4265ef","en_contact.md":"6c6341cc","memo_git_project.md":"3cd8389a","en_memo_index.md":"17bd0fe3","memo_apple_macos.md":"88172686","memo_web_vmodel-loop-error.md":"3f036c33","memo_git_config.md":"9ac430e2","memo_via_parsec.md":"d3673510","memo_git_common.md":"6041d84a","memo_microsoft_remote-signed.md":"43de7bb7","index.md":"b13051b3","memo_apple_homebrew.md":"c57edf55","about.md":"40cf4e5b","bookmarks.md":"f9524b46"}
